nimporter.py
nimporter_cli.py
nimporter-1.0.2.dist-info/LICENSE
nimporter-1.0.2.dist-info/METADATA
nimporter-1.0.2.dist-info/WHEEL
nimporter-1.0.2.dist-info/entry_points.txt
nimporter-1.0.2.dist-info/top_level.txt
nimporter-1.0.2.dist-info/RECORD
