Metadata-Version: 2.1
Name: nimporter
Version: 1.0.2
Summary: Compile Nim extensions for Python when imported!
Home-page: http://github.com/Pebaz/Nimporter
Author: http://github.com/Pebaz
License: MIT
Platform: UNKNOWN
